{"412a84cf508d3d849f4a45de494c9358":{"statistic":{"failed":0,"broken":0,"skipped":0,"passed":8,"unknown":0,"total":8},"items":[{"uid":"38bf992fc45eda70","reportUrl":"https://ZhikharevAl.github.io/TestNest/18//#testresult/38bf992fc45eda70","status":"passed","time":{"start":1727347260209,"stop":1727347261303,"duration":1094}},{"uid":"fd09be3a0d869709","reportUrl":"https://ZhikharevAl.github.io/TestNest/15//#testresult/fd09be3a0d869709","status":"passed","time":{"start":1727346975191,"stop":1727346976313,"duration":1122}},{"uid":"fae08efd08c7e5e4","reportUrl":"https://ZhikharevAl.github.io/TestNest/13//#testresult/fae08efd08c7e5e4","status":"passed","time":{"start":1727305366560,"stop":1727305367259,"duration":699}},{"uid":"a193681f283920b0","reportUrl":"https://ZhikharevAl.github.io/TestNest/11//#testresult/a193681f283920b0","status":"passed","time":{"start":1727305185300,"stop":1727305185932,"duration":632}},{"uid":"322f1dd8672a8eb6","reportUrl":"https://ZhikharevAl.github.io/TestNest/10//#testresult/322f1dd8672a8eb6","status":"passed","time":{"start":1727258248545,"stop":1727258249166,"duration":621}},{"uid":"cc3c43682c76979a","reportUrl":"https://ZhikharevAl.github.io/TestNest/7//#testresult/cc3c43682c76979a","status":"passed","time":{"start":1727235457714,"stop":1727235458586,"duration":872}},{"uid":"5264d7649cd1cefd","reportUrl":"https://ZhikharevAl.github.io/TestNest/6//#testresult/5264d7649cd1cefd","status":"passed","time":{"start":1727234277873,"stop":1727234278667,"duration":794}},{"uid":"749eea484378b0bb","reportUrl":"https://ZhikharevAl.github.io/TestNest/5//#testresult/749eea484378b0bb","status":"passed","time":{"start":1727230688176,"stop":1727230688894,"duration":718}}]},"643221714b3c9eed6111e4bd98d23fae":{"statistic":{"failed":0,"broken":0,"skipped":0,"passed":2,"unknown":0,"total":2},"items":[{"uid":"9da1897d41d92182","reportUrl":"https://ZhikharevAl.github.io/TestNest/28//#testresult/9da1897d41d92182","status":"passed","time":{"start":1727230961218,"stop":1727230962241,"duration":1023}},{"uid":"1d9df573ee0827c1","reportUrl":"https://ZhikharevAl.github.io/TestNest/27//#testresult/1d9df573ee0827c1","status":"passed","time":{"start":1727230496840,"stop":1727230498220,"duration":1380}}]},"4fc7e178233ca1b1d3084d53a584f20d":{"statistic":{"failed":0,"broken":1,"skipped":0,"passed":8,"unknown":0,"total":9},"items":[{"uid":"fa081fb26b369a9","reportUrl":"https://ZhikharevAl.github.io/TestNest/18//#testresult/fa081fb26b369a9","status":"passed","time":{"start":1727347258021,"stop":1727347258022,"duration":1}},{"uid":"c2b85a4b143fc0d","reportUrl":"https://ZhikharevAl.github.io/TestNest/15//#testresult/c2b85a4b143fc0d","status":"passed","time":{"start":1727346972989,"stop":1727346972989,"duration":0}},{"uid":"5e939571606ab610","reportUrl":"https://ZhikharevAl.github.io/TestNest/13//#testresult/5e939571606ab610","status":"passed","time":{"start":1727305364194,"stop":1727305364194,"duration":0}},{"uid":"575e5fb3b268e5fd","reportUrl":"https://ZhikharevAl.github.io/TestNest/11//#testresult/575e5fb3b268e5fd","status":"passed","time":{"start":1727305183295,"stop":1727305183295,"duration":0}},{"uid":"9946a667d5804912","reportUrl":"https://ZhikharevAl.github.io/TestNest/10//#testresult/9946a667d5804912","status":"passed","time":{"start":1727258246621,"stop":1727258246621,"duration":0}},{"uid":"89f19173916b0d85","reportUrl":"https://ZhikharevAl.github.io/TestNest/8//#testresult/89f19173916b0d85","status":"broken","statusDetails":"requests.exceptions.HTTPError: 404 Client Error: Not Found for url: https://a031-95-32-133-30.ngrok-free.app/api/create","time":{"start":1727257935168,"stop":1727257935168,"duration":0}},{"uid":"8ca79a24bfc8b937","reportUrl":"https://ZhikharevAl.github.io/TestNest/7//#testresult/8ca79a24bfc8b937","status":"passed","time":{"start":1727235454935,"stop":1727235454935,"duration":0}},{"uid":"a7b1d1a46952b95b","reportUrl":"https://ZhikharevAl.github.io/TestNest/6//#testresult/a7b1d1a46952b95b","status":"passed","time":{"start":1727234275506,"stop":1727234275507,"duration":1}},{"uid":"6e0be8d53994f8ef","reportUrl":"https://ZhikharevAl.github.io/TestNest/5//#testresult/6e0be8d53994f8ef","status":"passed","time":{"start":1727230686016,"stop":1727230686016,"duration":0}}]},"9d79d9e140415fb9f4a303addeb457db":{"statistic":{"failed":0,"broken":1,"skipped":0,"passed":8,"unknown":0,"total":9},"items":[{"uid":"1745c346d0082fc7","reportUrl":"https://ZhikharevAl.github.io/TestNest/18//#testresult/1745c346d0082fc7","status":"passed","time":{"start":1727347259464,"stop":1727347259834,"duration":370}},{"uid":"8110f39338515a92","reportUrl":"https://ZhikharevAl.github.io/TestNest/15//#testresult/8110f39338515a92","status":"passed","time":{"start":1727346974444,"stop":1727346974809,"duration":365}},{"uid":"e2b26a8a752befa7","reportUrl":"https://ZhikharevAl.github.io/TestNest/13//#testresult/e2b26a8a752befa7","status":"passed","time":{"start":1727305365516,"stop":1727305365871,"duration":355}},{"uid":"177540fa1e8152a9","reportUrl":"https://ZhikharevAl.github.io/TestNest/11//#testresult/177540fa1e8152a9","status":"passed","time":{"start":1727305184657,"stop":1727305184972,"duration":315}},{"uid":"454a508ef37f3e8a","reportUrl":"https://ZhikharevAl.github.io/TestNest/10//#testresult/454a508ef37f3e8a","status":"passed","time":{"start":1727258247909,"stop":1727258248227,"duration":318}},{"uid":"f98678aa8b0cfc44","reportUrl":"https://ZhikharevAl.github.io/TestNest/8//#testresult/f98678aa8b0cfc44","status":"broken","statusDetails":"requests.exceptions.HTTPError: 404 Client Error: Not Found for url: https://a031-95-32-133-30.ngrok-free.app/api/getAll","time":{"start":1727257985828,"stop":1727257985863,"duration":35}},{"uid":"47ef091a208f0eb","reportUrl":"https://ZhikharevAl.github.io/TestNest/7//#testresult/47ef091a208f0eb","status":"passed","time":{"start":1727235456697,"stop":1727235457135,"duration":438}},{"uid":"ff24ff0db6d8528a","reportUrl":"https://ZhikharevAl.github.io/TestNest/6//#testresult/ff24ff0db6d8528a","status":"passed","time":{"start":1727234277086,"stop":1727234277476,"duration":390}},{"uid":"e5220fa9e065f7e6","reportUrl":"https://ZhikharevAl.github.io/TestNest/5//#testresult/e5220fa9e065f7e6","status":"passed","time":{"start":1727230687451,"stop":1727230687809,"duration":358}}]},"f714298063a5b173ddfc742f5b450f5b":{"statistic":{"failed":0,"broken":0,"skipped":0,"passed":2,"unknown":0,"total":2},"items":[{"uid":"7918d8c3bafe677b","reportUrl":"https://ZhikharevAl.github.io/TestNest/28//#testresult/7918d8c3bafe677b","status":"passed","time":{"start":1727230961214,"stop":1727230962476,"duration":1262}},{"uid":"87b5b371717ce640","reportUrl":"https://ZhikharevAl.github.io/TestNest/27//#testresult/87b5b371717ce640","status":"passed","time":{"start":1727230496844,"stop":1727230498436,"duration":1592}}]},"77fef8bb3bf3b1641b66b2e3949b6a4c":{"statistic":{"failed":0,"broken":0,"skipped":0,"passed":2,"unknown":0,"total":2},"items":[{"uid":"9fa859894a4a4c93","reportUrl":"https://ZhikharevAl.github.io/TestNest/28//#testresult/9fa859894a4a4c93","status":"passed","time":{"start":1727230961224,"stop":1727230962336,"duration":1112}},{"uid":"ba185268e8f99514","reportUrl":"https://ZhikharevAl.github.io/TestNest/27//#testresult/ba185268e8f99514","status":"passed","time":{"start":1727230496859,"stop":1727230498314,"duration":1455}}]},"e812bf5b63e5885d57ac9daef262aef1":{"statistic":{"failed":0,"broken":0,"skipped":0,"passed":2,"unknown":0,"total":2},"items":[{"uid":"1da2388a3f2ffebe","reportUrl":"https://ZhikharevAl.github.io/TestNest/28//#testresult/1da2388a3f2ffebe","status":"passed","time":{"start":1727230961233,"stop":1727230962354,"duration":1121}},{"uid":"b36218883b9d4fc4","reportUrl":"https://ZhikharevAl.github.io/TestNest/27//#testresult/b36218883b9d4fc4","status":"passed","time":{"start":1727230496848,"stop":1727230498377,"duration":1529}}]},"57eefbb9ff7015b44fba60a77b0003f9":{"statistic":{"failed":0,"broken":1,"skipped":0,"passed":8,"unknown":0,"total":9},"items":[{"uid":"3b0f68b826aa7078","reportUrl":"https://ZhikharevAl.github.io/TestNest/18//#testresult/3b0f68b826aa7078","status":"passed","time":{"start":1727347258765,"stop":1727347259114,"duration":349}},{"uid":"950bd40ee7240a71","reportUrl":"https://ZhikharevAl.github.io/TestNest/15//#testresult/950bd40ee7240a71","status":"passed","time":{"start":1727346973685,"stop":1727346974042,"duration":357}},{"uid":"d21c48a496dd9efe","reportUrl":"https://ZhikharevAl.github.io/TestNest/13//#testresult/d21c48a496dd9efe","status":"passed","time":{"start":1727305364871,"stop":1727305365187,"duration":316}},{"uid":"a954b038b50aa6b0","reportUrl":"https://ZhikharevAl.github.io/TestNest/11//#testresult/a954b038b50aa6b0","status":"passed","time":{"start":1727305184016,"stop":1727305184335,"duration":319}},{"uid":"7b3a943f5125967c","reportUrl":"https://ZhikharevAl.github.io/TestNest/10//#testresult/7b3a943f5125967c","status":"passed","time":{"start":1727258247251,"stop":1727258247595,"duration":344}},{"uid":"21a01d242b2dfa94","reportUrl":"https://ZhikharevAl.github.io/TestNest/8//#testresult/21a01d242b2dfa94","status":"broken","statusDetails":"requests.exceptions.HTTPError: 404 Client Error: Not Found for url: https://a031-95-32-133-30.ngrok-free.app/api/create","time":{"start":1727257960489,"stop":1727257960489,"duration":0}},{"uid":"3cecf44e1aa46b50","reportUrl":"https://ZhikharevAl.github.io/TestNest/7//#testresult/3cecf44e1aa46b50","status":"passed","time":{"start":1727235455823,"stop":1727235456262,"duration":439}},{"uid":"a1b4518041e8539d","reportUrl":"https://ZhikharevAl.github.io/TestNest/6//#testresult/a1b4518041e8539d","status":"passed","time":{"start":1727234276300,"stop":1727234276690,"duration":390}},{"uid":"28db050cbaed3556","reportUrl":"https://ZhikharevAl.github.io/TestNest/5//#testresult/28db050cbaed3556","status":"passed","time":{"start":1727230686737,"stop":1727230687095,"duration":358}}]},"6faae56fe88ded7b4d2032f7aba719da":{"statistic":{"failed":0,"broken":0,"skipped":0,"passed":8,"unknown":0,"total":8},"items":[{"uid":"bf2bfb8ce4f3e8f9","reportUrl":"https://ZhikharevAl.github.io/TestNest/18//#testresult/bf2bfb8ce4f3e8f9","status":"passed","time":{"start":1727347261660,"stop":1727347262722,"duration":1062}},{"uid":"7f62cc9af6a07ed1","reportUrl":"https://ZhikharevAl.github.io/TestNest/15//#testresult/7f62cc9af6a07ed1","status":"passed","time":{"start":1727346976665,"stop":1727346977770,"duration":1105}},{"uid":"42e461d6828a826c","reportUrl":"https://ZhikharevAl.github.io/TestNest/13//#testresult/42e461d6828a826c","status":"passed","time":{"start":1727305367581,"stop":1727305368601,"duration":1020}},{"uid":"a3992ce6b598f41d","reportUrl":"https://ZhikharevAl.github.io/TestNest/11//#testresult/a3992ce6b598f41d","status":"passed","time":{"start":1727305186250,"stop":1727305187297,"duration":1047}},{"uid":"92a4caa3aa2cb54e","reportUrl":"https://ZhikharevAl.github.io/TestNest/10//#testresult/92a4caa3aa2cb54e","status":"passed","time":{"start":1727258249476,"stop":1727258250425,"duration":949}},{"uid":"5127702d05f2e92d","reportUrl":"https://ZhikharevAl.github.io/TestNest/7//#testresult/5127702d05f2e92d","status":"passed","time":{"start":1727235459021,"stop":1727235460334,"duration":1313}},{"uid":"f6222c515d00f1c4","reportUrl":"https://ZhikharevAl.github.io/TestNest/6//#testresult/f6222c515d00f1c4","status":"passed","time":{"start":1727234279059,"stop":1727234280251,"duration":1192}},{"uid":"52646e1ecc04f8be","reportUrl":"https://ZhikharevAl.github.io/TestNest/5//#testresult/52646e1ecc04f8be","status":"passed","time":{"start":1727230689268,"stop":1727230690356,"duration":1088}}]}}